CHANGELOG.txt
LICENSE.txt
MANIFEST.in
README.md
setup.py
pyrandmeme/__init__.py
pyrandmeme.egg-info/PKG-INFO
pyrandmeme.egg-info/SOURCES.txt
pyrandmeme.egg-info/dependency_links.txt
pyrandmeme.egg-info/requires.txt
pyrandmeme.egg-info/top_level.txt