Metadata-Version: 1.1
Name: pyrandmeme
Version: 0.0.4
Summary: Random memes for discord.py
Home-page: UNKNOWN
Author: Poggy
Author-email: poggywastaken123@gmail.com
License: UNKNOWN
Keywords: memes
Platform: UNKNOWN
Classifier: Development Status :: 5 - Production/Stable
Classifier: Intended Audience :: Education
Classifier: Operating System :: Microsoft :: Windows :: Windows 10
Classifier: License :: OSI Approved :: MIT License
Classifier: Programming Language :: Python :: 3
